prlps_fakeua/__init__.py
prlps_fakeua/fakeua.py
prlps_text_replacer/__init__.py
prlps_text_replacer-0.0.1.dist-info/LICENSE.txt
prlps_text_replacer-0.0.1.dist-info/METADATA
prlps_text_replacer-0.0.1.dist-info/WHEEL
prlps_text_replacer-0.0.1.dist-info/top_level.txt
prlps_text_replacer-0.0.1.dist-info/RECORD
