Metadata-Version: 2.1
Name: prlps_text_replacer
Version: 0.0.1
Summary: замена слов и фраз по словарям замен с сохранением исходного регистра
Home-page: https://github.com/prolapser/prlps_text_replacer
Author: prolapser
License: LICENSE.txt
Classifier: Development Status :: 4 - Beta
Classifier: Intended Audience :: Developers
Classifier: License :: OSI Approved :: MIT License
Classifier: Operating System :: OS Independent
Requires-Python: >=3.10
License-File: LICENSE.txt
